{
    "dl4-eclpk1": {
        "root": "eclpk1",
        "produit": "PWX4",
        "techno": "ct",
        "ratio": "2000",
        "Nki": "0",
        "Akv": "1",
        "Aki": "1",
        "Bkv": "1",
        "Bki": "1",
        "Ckv": "1",
        "Cki": "1"
    },   
    "dl12-seclkpk234": {
        "root": ["eclpk2","eclpk3","eclpk4","*"],
        "produit": "BLX12",
        "techno": ["ct","ct","ct","ct"],
        "ratio": ["1000","1000","1000","1000"]
    },
    "dl4-eclpub2": {
        "root": "eclpub2",
        "produit": "PWX4",
        "techno": "ct",
        "ratio": "1000",
        "Nki": "0",
        "Akv": "1",
        "Aki": "1",
        "Bkv": "1",
        "Bki": "1",
        "Ckv": "1",
        "Cki": "1"
    },   
    "dl12-divers": {
        "root": ["divers_1","chauffage","eclpkpub2","*"],
        "produit": "BLX12",
        "techno": ["ct","ct","ct","ct"],
        "ratio": ["1000","2000","1000","1000"]
    },
    "dl4-main": {
        "root": "main",
        "produit": "BLX4",
        "techno": "rogowski",
        "ratio": "3003",
        "Nki": "0",
        "Akv": "1",
        "Aki": "1",
        "Bkv": "1",
        "Bki": "1",
        "Ckv": "1",
        "Cki": "1"
    },
    "dl4-froid": {
        "root": "froid",
        "produit": "BLX4",
        "techno": "ct",
        "ratio": "3000",
        "Nki": "0",
        "Akv": "1",
        "Aki": "1",
        "Bkv": "1",
        "Bki": "1",
        "Ckv": "1",
        "Cki": "1"
    }, 
       "dl4-labo": {
        "root": "labo",
        "produit": "BLX4",
        "techno": "ct",
        "ratio": "1000",
        "Nki": "0",
        "Akv": "1",
        "Aki": "1",
        "Bkv": "1",
        "Bki": "1",
        "Ckv": "1",
        "Cki": "1"
    },

    "dl12-main1": {
        "root": ["divers_1","chauffage","eclpkpub2","*"],
        "produit": "BLX12",
        "techno": ["ct","ct","ct","ct"],
        "ratio": ["1000","2000","1000","1000"]
    },
    "dl12-main2": {
        "root": ["divers_1","chauffage","eclpkpub2","*"],
        "produit": "BLX12",
        "techno": ["ct","ct","ct","ct"],
        "ratio": ["1000","2000","1000","1000"]
    },
    "dl12-dmain3": {
        "root": ["divers_1","chauffage","eclpkpub2","*"],
        "produit": "BLX12",
        "techno": ["ct","ct","ct","ct"],
        "ratio": ["1000","2000","1000","1000"]
    },
    "dl12-main4": {
        "root": ["divers_1","chauffage","eclpkpub2","*"],
        "produit": "BLX12",
        "techno": ["ct","ct","ct","ct"],
        "ratio": ["1000","2000","1000","1000"]
    },
    "dl12-tgbt1": {
        "root": ["froid","tdcaisses","tdlabo","*"],
        "produit": "BLX12",
        "techno": ["ct","ct","ct","ct"],
        "ratio": ["1000","1000","4000","1000"]
    },
    "dl12-tgbt1": {
        "root": ["rooftop2","tdbureaux","rooftop1","*"],
        "produit": "BLX12",
        "techno": ["ct","ct","ct","ct"],
        "ratio": ["1000","1000","1000","1000"]
    }
 }