{
    "1": {
        "Name": "FraisEmbale1",
        "status": {},
        "alias_sonde": "TherAir",
        "alias_cutout": "CutoutTemp",
        "poste": "NA",
        "categorie": "devpos",
        "genre": "vitrine+",
        "device": "AK-CC550"
    },
    "2": {
        "Name": "TGBacFrais2",
        "status": {},
        "alias_sonde": "TherAir",
        "alias_cutout": "CutoutTemp",
        "poste": "NA",
        "categorie": "devpos",
        "genre": "bac+",
        "device": "AK-CC550"
    },
    "3": {
        "Name": "BacFrais3",
        "status": {},
        "alias_sonde": "TherAir",
        "alias_cutout": "CutoutTemp",
        "poste": "NA",
        "categorie": "devpos",
        "genre": "bac+",
        "device": "AK-CC550"
    },
    "4": {
        "Name": "TGBacFrais4",
        "status": {},
        "alias_sonde": "TherAir",
        "alias_cutout": "CutoutTemp",
        "poste": "NA",
        "categorie": "devpos",
        "genre": "bac+",
        "device": "AK-CC550"
    },
    "10": {
        "Name": "TGBacSurg10",
        "status": {},
        "alias_sonde": "TherAir",
        "alias_cutout": "CutoutTemp",
        "poste": "NA",
        "categorie": "devneg",
        "genre": "bac-",
        "device": "AK-CC550"
    },
    "11": {
        "Name": "SurgeleMixte11",
        "status": {},
        "alias_sonde": "TherAir",
        "alias_cutout": "CutoutTemp",
        "poste": "NA",
        "categorie": "devneg",
        "genre": "vitrine-",
        "device": "AK-CC550"
    },
    "13": {
        "Name": "SurgeleMixte13",
        "status": {},
        "alias_sonde": "TherAir",
        "alias_cutout": "CutoutTemp",
        "poste": "NA",
        "categorie": "devneg",
        "genre": "vitrine-",
        "device": "AK-CC550"
    },
    "14": {
        "Name": "BacSurgele14",
        "status": {},
        "alias_sonde": "TherAir",
        "alias_cutout": "CutoutTemp",
        "poste": "NA",
        "categorie": "devneg",
        "genre": "bac-",
        "device": "AK-CC550"
    },
    "15": {
        "Name": "BacSurgele15",
        "status": {},
        "alias_sonde": "TherAir",
        "alias_cutout": "CutoutTemp",
        "poste": "NA",
        "categorie": "devneg",
        "genre": "bac-",
        "device": "AK-CC550"
    },
    "16": {
        "Name": "BacSurgele16",
        "status": {},
        "alias_sonde": "TherAir",
        "alias_cutout": "CutoutTemp",
        "poste": "NA",
        "categorie": "devneg",
        "genre": "bac-",
        "device": "AK-CC550"
    },
    "17": {
        "Name": "TGBacSurg17",
        "status": {},
        "alias_sonde": "TherAir",
        "alias_cutout": "CutoutTemp",
        "poste": "NA",
        "categorie": "devneg",
        "genre": "bac-",
        "device": "AK-CC550"
    },
    "18": {
        "Name": "BacSurgele18",
        "status": {},
        "alias_sonde": "TherAir",
        "alias_cutout": "CutoutTemp",
        "poste": "NA",
        "categorie": "devneg",
        "genre": "bac-",
        "device": "AK-CC550"
    },
    "19": {
        "Name": "BacSurgele19",
        "status": {},
        "alias_sonde": "TherAir",
        "alias_cutout": "CutoutTemp",
        "poste": "NA",
        "categorie": "devneg",
        "genre": "bac-",
        "device": "AK-CC550"
    },
    "21": {
        "Name": "BacSurgele21",
        "status": {},
        "alias_sonde": "TherAir",
        "alias_cutout": "CutoutTemp",
        "poste": "NA",
        "categorie": "devneg",
        "genre": "bac-",
        "device": "AK-CC550"
    },
    "22": {
        "Name": "BacSurgele22",
        "status": {},
        "alias_sonde": "TherAir",
        "alias_cutout": "CutoutTemp",
        "poste": "NA",
        "categorie": "devneg",
        "genre": "bac-",
        "device": "AK-CC550"
    },
    "23": {
        "Name": "CharcuteLS23",
        "status": {},
        "alias_sonde": "TherAir",
        "alias_cutout": "CutoutTemp",
        "poste": "NA",
        "categorie": "devpos",
        "genre": "vitrine+",
        "device": "AK-CC550"
    },
    "24": {
        "Name": "CharcuteLS24",
        "status": {},
        "alias_sonde": "TherAir",
        "alias_cutout": "CutoutTemp",
        "poste": "NA",
        "categorie": "devpos",
        "genre": "vitrine+",
        "device": "AK-CC550"
    },
    "25": {
        "Name": "CharcuteLS25",
        "status": {},
        "alias_sonde": "TherAir",
        "alias_cutout": "CutoutTemp",
        "poste": "NA",
        "categorie": "devpos",
        "genre": "vitrine+",
        "device": "AK-CC550"
    },
    "28": {
        "Name": "BacPromo28",
        "status": {},
        "alias_sonde": "TherAir",
        "alias_cutout": "CutoutTemp",
        "poste": "NA",
        "categorie": "devpos",
        "genre": "bac+",
        "device": "AK-CC550"
    },
    "29": {
        "Name": "BoucherieLS29",
        "status": {},
        "alias_sonde": "TherAir",
        "alias_cutout": "CutoutTemp",
        "poste": "NA",
        "categorie": "devpos",
        "genre": "vitrine+",
        "device": "AK-CC550"
    },
    "30": {
        "Name": "BoucherieLS30",
        "status": {},
        "alias_sonde": "TherAir",
        "alias_cutout": "CutoutTemp",
        "poste": "NA",
        "categorie": "devpos",
        "genre": "vitrine+",
        "device": "AK-CC550"
    },
    "31": {
        "Name": "BoucherieLS31",
        "status": {},
        "alias_sonde": "TherAir",
        "alias_cutout": "CutoutTemp",
        "poste": "NA",
        "categorie": "devpos",
        "genre": "vitrine+",
        "device": "AK-CC550"
    },
    "32": {
        "Name": "FromageLS32",
        "status": {},
        "alias_sonde": "TherAir",
        "alias_cutout": "CutoutTemp",
        "poste": "NA",
        "categorie": "devpos",
        "genre": "vitrine+",
        "device": "AK-CC550"
    },
    "33": {
        "Name": "FromageLS33",
        "status": {},
        "alias_sonde": "TherAir",
        "alias_cutout": "CutoutTemp",
        "poste": "NA",
        "categorie": "devpos",
        "genre": "vitrine+",
        "device": "AK-CC550"
    },
    "35": {
        "Name": "TraiteurLS35",
        "status": {},
        "alias_sonde": "TherAir",
        "alias_cutout": "CutoutTemp",
        "poste": "NA",
        "categorie": "devpos",
        "genre": "vitrine+",
        "device": "AK-CC550"
    },
    "36": {
        "Name": "TraiteurLS36",
        "status": {},
        "alias_sonde": "TherAir",
        "alias_cutout": "CutoutTemp",
        "poste": "NA",
        "categorie": "devpos",
        "genre": "vitrine+",
        "device": "AK-CC550"
    },
    "37": {
        "Name": "TraiteurLS37",
        "status": {},
        "alias_sonde": "TherAir",
        "alias_cutout": "CutoutTemp",
        "poste": "NA",
        "categorie": "devpos",
        "genre": "vitrine+",
        "device": "AK-CC550"
    },
    "38": {
        "Name": "UltraFrais38",
        "status": {},
        "alias_sonde": "TherAir",
        "alias_cutout": "CutoutTemp",
        "poste": "NA",
        "categorie": "devpos",
        "genre": "vitrine+",
        "device": "AK-CC550"
    },
    "39": {
        "Name": "UltraFrais39",
        "status": {},
        "alias_sonde": "TherAir",
        "alias_cutout": "CutoutTemp",
        "poste": "NA",
        "categorie": "devpos",
        "genre": "vitrine+",
        "device": "AK-CC550"
    },
    "40": {
        "Name": "UltraFrais40",
        "status": {},
        "alias_sonde": "TherAir",
        "alias_cutout": "CutoutTemp",
        "poste": "NA",
        "categorie": "devpos",
        "genre": "vitrine+",
        "device": "AK-CC550"
    },
    "41": {
        "Name": "UltraFrais41",
        "status": {},
        "alias_sonde": "TherAir",
        "alias_cutout": "CutoutTemp",
        "poste": "NA",
        "categorie": "devpos",
        "genre": "vitrine+",
        "device": "AK-CC550"
    },
    "42": {
        "Name": "UltraFrais42",
        "status": {},
        "alias_sonde": "TherAir",
        "alias_cutout": "CutoutTemp",
        "poste": "NA",
        "categorie": "devpos",
        "genre": "vitrine+",
        "device": "AK-CC550"
    },
    "43": {
        "Name": "UltraFrais43",
        "status": {},
        "alias_sonde": "TherAir",
        "alias_cutout": "CutoutTemp",
        "poste": "NA",
        "categorie": "devpos",
        "genre": "vitrine+",
        "device": "AK-CC550"
    },
    "44": {
        "Name": "FromageLS44",
        "status": {},
        "alias_sonde": "TherAir",
        "alias_cutout": "CutoutTemp",
        "poste": "NA",
        "categorie": "devpos",
        "genre": "vitrine+",
        "device": "AK-CC550"
    },
    "45": {
        "Name": "FromageLS45",
        "status": {},
        "alias_sonde": "TherAir",
        "alias_cutout": "CutoutTemp",
        "poste": "NA",
        "categorie": "devpos",
        "genre": "vitrine+",
        "device": "AK-CC550"
    },
    "46": {
        "Name": "FromageLS46",
        "status": {},
        "alias_sonde": "TherAir",
        "alias_cutout": "CutoutTemp",
        "poste": "NA",
        "categorie": "devpos",
        "genre": "vitrine+",
        "device": "AK-CC550"
    },
    "47": {
        "Name": "4eGamme47",
        "status": {},
        "alias_sonde": "TherAir",
        "alias_cutout": "CutoutTemp",
        "poste": "NA",
        "categorie": "devpos",
        "genre": "vitrine+",
        "device": "AK-CC550"
    },
    "48": {
        "Name": "4eGamme48",
        "status": {},
        "alias_sonde": "TherAir",
        "alias_cutout": "CutoutTemp",
        "poste": "NA",
        "categorie": "devpos",
        "genre": "vitrine+",
        "device": "AK-CC550"
    },
    "50": {
        "Name": "AntiGaspiSV50",
        "status": {},
        "alias_sonde": "TherAir",
        "alias_cutout": "CutoutTemp",
        "poste": "NA",
        "categorie": "devpos",
        "genre": "bac+",
        "device": "AK-CC550"
    },
    "51": {
        "Name": "TradBoucherie51",
        "status": {},
        "alias_sonde": "TherAir",
        "alias_cutout": "CutoutTemp",
        "poste": "NA",
        "categorie": "devpos",
        "genre": "vitrine+",
        "device": "AK-CC550"
    },
    "52": {
        "Name": "TradBoucherie52",
        "status": {},
        "alias_sonde": "TherAir",
        "alias_cutout": "CutoutTemp",
        "poste": "NA",
        "categorie": "devpos",
        "genre": "vitrine+",
        "device": "AK-CC550"
    },
    "53": {
        "Name": "TradBoucherie53",
        "status": {},
        "alias_sonde": "TherAir",
        "alias_cutout": "CutoutTemp",
        "poste": "NA",
        "categorie": "devpos",
        "genre": "vitrine+",
        "device": "AK-CC550"
    },
    "54": {
        "Name": "TradBoucherie54",
        "status": {},
        "alias_sonde": "TherAir",
        "alias_cutout": "CutoutTemp",
        "poste": "NA",
        "categorie": "devpos",
        "genre": "vitrine+",
        "device": "AK-CC550"
    },
    "55": {
        "Name": "TradCharcuterie55",
        "status": {},
        "alias_sonde": "TherAir",
        "alias_cutout": "CutoutTemp",
        "poste": "NA",
        "categorie": "devpos",
        "genre": "vitrine+",
        "device": "AK-CC550"
    },
    "56": {
        "Name": "TradCharcuterie56",
        "status": {},
        "alias_sonde": "TherAir",
        "alias_cutout": "CutoutTemp",
        "poste": "NA",
        "categorie": "devpos",
        "genre": "vitrine+",
        "device": "AK-CC550"
    },
    "57": {
        "Name": "TradCharcuterie57",
        "status": {},
        "alias_sonde": "TherAir",
        "alias_cutout": "CutoutTemp",
        "poste": "NA",
        "categorie": "devpos",
        "genre": "vitrine+",
        "device": "AK-CC550"
    },
    "58": {
        "Name": "TradCharcuterie58",
        "status": {},
        "alias_sonde": "TherAir",
        "alias_cutout": "CutoutTemp",
        "poste": "NA",
        "categorie": "devpos",
        "genre": "vitrine+",
        "device": "AK-CC550"
    },
    "59": {
        "Name": "SaurisserieLS59",
        "status": {},
        "alias_sonde": "TherAir",
        "alias_cutout": "CutoutTemp",
        "poste": "NA",
        "categorie": "devpos",
        "genre": "vitrine+",
        "device": "AK-CC550"
    },
    "60": {
        "Name": "SasFrais60",
        "status": {},
        "alias_sonde": "TherAir",
        "alias_cutout": "CutoutTemp",
        "poste": "NA",
        "categorie": "devpos",
        "genre": "CF+",
        "device": "AK-CC550"
    },
    "61": {
        "Name": "SasSurgele61",
        "status": {},
        "alias_sonde": "TherAir",
        "alias_cutout": "CutoutTemp",
        "poste": "NA",
        "categorie": "devneg",
        "genre": "CF-",
        "device": "AK-CC550"
    },
    "62": {
        "Name": "CFBarquettes62",
        "status": {},
        "alias_sonde": "TherAir",
        "alias_cutout": "CutoutTemp",
        "poste": "NA",
        "categorie": "devpos",
        "genre": "CF+",
        "device": "AK-CC550"
    },
    "63": {
        "Name": "CFCharcuterie63",
        "status": {},
        "alias_sonde": "TherAir",
        "alias_cutout": "CutoutTemp",
        "poste": "NA",
        "categorie": "devpos",
        "genre": "CF+",
        "device": "AK-CC550"
    },
    "64": {
        "Name": "CFFetLegumes64",
        "status": {},
        "alias_sonde": "TherAir",
        "alias_cutout": "CutoutTemp",
        "poste": "NA",
        "categorie": "devpos",
        "genre": "CF+",
        "device": "AK-CC550"
    },
    "65": {
        "Name": "CFFromage65",
        "status": {},
        "alias_sonde": "TherAir",
        "alias_cutout": "CutoutTemp",
        "poste": "NA",
        "categorie": "devpos",
        "genre": "CF+",
        "device": "AK-CC550"
    },
    "66": {
        "Name": "LaboFromage66",
        "status": {},
        "alias_sonde": "TherAir",
        "alias_cutout": "CutoutTemp",
        "poste": "NA",
        "categorie": "devpos",
        "genre": "CF+",
        "device": "AK-CC550"
    },
    "67": {
        "Name": "CFCharcuterie67",
        "status": {},
        "alias_sonde": "TherAir",
        "alias_cutout": "CutoutTemp",
        "poste": "NA",
        "categorie": "devpos",
        "genre": "CF+",
        "device": "AK-CC550"
    },
    "68": {
        "Name": "LaboCharcuterie68",
        "status": {},
        "alias_sonde": "TherAir",
        "alias_cutout": "CutoutTemp",
        "poste": "NA",
        "categorie": "devpos",
        "genre": "CF+",
        "device": "AK-CC550"
    },
    "69": {
        "Name": "CFCarcasses69",
        "status": {},
        "alias_sonde": "TherAir",
        "alias_cutout": "CutoutTemp",
        "poste": "NA",
        "categorie": "devpos",
        "genre": "CF+",
        "device": "AK-CC550"
    },
    "70": {
        "Name": "CFBarquettes70",
        "status": {},
        "alias_sonde": "TherAir",
        "alias_cutout": "CutoutTemp",
        "poste": "NA",
        "categorie": "devpos",
        "genre": "CF+",
        "device": "AK-CC550"
    },
    "71": {
        "Name": "CFPFinis71",
        "status": {},
        "alias_sonde": "TherAir",
        "alias_cutout": "CutoutTemp",
        "poste": "NA",
        "categorie": "devpos",
        "genre": "CF+",
        "device": "AK-CC550"
    },
    "72": {
        "Name": "LocalDechet72",
        "status": {},
        "alias_sonde": "TherAir",
        "alias_cutout": "CutoutTemp",
        "poste": "NA",
        "categorie": "devpos",
        "genre": "CF+",
        "device": "AK-CC550"
    },
    "73": {
        "Name": "LaboBoucherie73",
        "status": {},
        "alias_sonde": "TherAir",
        "alias_cutout": "CutoutTemp",
        "poste": "NA",
        "categorie": "devpos",
        "genre": "CF+",
        "device": "AK-CC550"
    },
    "74": {
        "Name": "CFPoissons74",
        "status": {},
        "alias_sonde": "TherAir",
        "alias_cutout": "CutoutTemp",
        "poste": "NA",
        "categorie": "devpos",
        "genre": "CF+",
        "device": "AK-CC550"
    },
    "75": {
        "Name": "LaboPoisson75",
        "status": {},
        "alias_sonde": "TherAir",
        "alias_cutout": "CutoutTemp",
        "poste": "NA",
        "categorie": "devpos",
        "genre": "CF+",
        "device": "AK-CC550"
    },
    "76": {
        "Name": "CFDrive76",
        "status": {},
        "alias_sonde": "TherAir",
        "alias_cutout": "CutoutTemp",
        "poste": "NA",
        "categorie": "devpos",
        "genre": "CF+",
        "device": "AK-CC550"
    },
    "80": {
        "Name": "CFSurgDivers80",
        "status": {},
        "alias_sonde": "TherAir",
        "alias_cutout": "CutoutTemp",
        "poste": "NA",
        "categorie": "devneg",
        "genre": "CF-",
        "device": "AK-CC550"
    },
    "81": {
        "Name": "CFSurgBoulang81",
        "status": {},
        "alias_sonde": "TherAir",
        "alias_cutout": "CutoutTemp",
        "poste": "NA",
        "categorie": "devneg",
        "genre": "CF-",
        "device": "AK-CC550"
    },
    "82": {
        "Name": "TGFrais82",
        "status": {},
        "alias_sonde": "TherAir",
        "alias_cutout": "CutoutTemp",
        "poste": "NA",
        "categorie": "devpos",
        "genre": "vitrine+",
        "device": "AK-CC550"
    },
    "83": {
        "Name": "TGFrais83",
        "status": {},
        "alias_sonde": "TherAir",
        "alias_cutout": "CutoutTemp",
        "poste": "NA",
        "categorie": "devpos",
        "genre": "vitrine+",
        "device": "AK-CC550"
    },
    "84": {
        "Name": "TGFrais84",
        "status": {},
        "alias_sonde": "TherAir",
        "alias_cutout": "CutoutTemp",
        "poste": "NA",
        "categorie": "devpos",
        "genre": "vitrine+",
        "device": "AK-CC550"
    },
    "85": {
        "Name": "TGFrais85",
        "status": {},
        "alias_sonde": "TherAir",
        "alias_cutout": "CutoutTemp",
        "poste": "NA",
        "categorie": "devpos",
        "genre": "vitrine+",
        "device": "AK-CC550"
    },
    "86": {
        "Name": "TGFrais86",
        "status": {},
        "alias_sonde": "TherAir",
        "alias_cutout": "CutoutTemp",
        "poste": "NA",
        "categorie": "devpos",
        "genre": "vitrine+",
        "device": "AK-CC550"
    },
    "87": {
        "Name": "TGFrais87",
        "status": {},
        "alias_sonde": "TherAir",
        "alias_cutout": "CutoutTemp",
        "poste": "NA",
        "categorie": "devpos",
        "genre": "vitrine+",
        "device": "AK-CC550"
    },
    "90": {
        "Name": "AspiPosiitve",
        "status": {},
        "alias_sonde": "na",
        "alias_cutout": "na",
        "poste": "NA",
        "categorie": "condpos",
        "genre": "condenseur",
        "device": "AK-PC781"
    },
    "91": {
        "Name": "AspiNeg",
        "status": {},
        "alias_sonde": "na",
        "alias_cutout": "na",
        "poste": "NA",
        "categorie": "condneg",
        "genre": "condenseur",
        "device": "AK-PC781"
    },
    "92": {
        "Name": "TraiteurLS92",
        "status": {},
        "alias_sonde": "TherAir",
        "alias_cutout": "CutoutTemp",
        "poste": "NA",
        "categorie": "devpos",
        "genre": "vitrine+",
        "device": "AK-CC550"
    },
    "93": {
        "Name": "TraiteurLS93",
        "status": {},
        "alias_sonde": "TherAir",
        "alias_cutout": "CutoutTemp",
        "poste": "NA",
        "categorie": "devpos",
        "genre": "vitrine+",
        "device": "AK-CC550"
    },
    "94": {
        "Name": "TraiteurLS94",
        "status": {},
        "alias_sonde": "TherAir",
        "alias_cutout": "CutoutTemp",
        "poste": "NA",
        "categorie": "devpos",
        "genre": "vitrine+",
        "device": "AK-CC550"
    }
}